[
	{ "s": "CACHE", "p": [18] },
	{ "s": "CAMELBACK", "p": [36, 14] },
	{ "s": "CAN", "p": [36, 5, 33, 18, 32, 30, 28, 14, 23, 19, 4, 2, 22, 17, 16, 13, 3] },
	{ "s": "CAPABILITIES", "p": [2] },
	{ "s": "CAPITOL", "p": [18, 14] },
	{ "s": "CAREFREE", "p": [30, 26] },
	{ "s": "CASE", "p": [24, 14, 3] },
	{ "s": "CENTER", "p": [35, 32, 17] },
	{ "s": "CENTERED", "p": [32] },
	{ "s": "CENTRAL", "p": [36, 14] },
	{ "s": "CHANGE", "p": [16, 34, 32, 12, 3, 19, 13, 5] },
	{ "s": "CHANGES", "p": [36, 5] },
	{ "s": "CHARACTER", "p": [36] },
	{ "s": "CHECK", "p": [34, 28, 23, 3] },
	{ "s": "CHECKING", "p": [28] },
	{ "s": "CHOICE", "p": [16, 4] },
	{ "s": "CHOICES", "p": [19, 18, 3] },
	{ "s": "CHROME", "p": [4] },
	{ "s": "CIRCLE", "p": [17] },
	{ "s": "CIRCUMFERENCE", "p": [17] },
	{ "s": "CITIES", "p": [30, 28, 26] },
	{ "s": "CITY", "p": [28, 20, 30, 26, 29, 36, 22] },
	{ "s": "CLEAN", "p": [5] },
	{ "s": "CLEAR", "p": [23, 30, 34, 17, 14, 3] },
	{ "s": "CLICK", "p": [32, 3, 28, 20, 16, 23, 14, 5, 19, 15, 13, 4, 36, 33, 31, 30, 29, 27, 26, 25, 24, 18, 17, 11, 9, 8] },
	{ "s": "CLICKING", "p": [5, 36, 31, 32, 28, 18, 16] },
	{ "s": "CLOSE", "p": [31, 3, 32, 18, 17, 33, 30, 23, 16, 15, 5, 4] },
	{ "s": "CLOSED", "p": [36] },
	{ "s": "CLOSER", "p": [34, 31, 29, 28, 19, 12, 8, 3] },
	{ "s": "CLOSES", "p": [36, 31, 5] },
	{ "s": "CLOSEST", "p": [20] },
	{ "s": "CLUTTER", "p": [28] },
	{ "s": "CM", "p": [16] },
	{ "s": "CODE", "p": [30, 25, 20, 28, 29, 3, 36, 22, 14] },
	{ "s": "CODES", "p": [30, 25] },
	{ "s": "COLLAPSE", "p": [34, 28, 5] },
	{ "s": "COLLAPSIBLE", "p": [5] },
	{ "s": "COLLAPSING", "p": [5] },
	{ "s": "COLLECTION", "p": [5] },
	{ "s": "COLOR", "p": [5] },
	{ "s": "COM", "p": [32, 3, 2] },
	{ "s": "COMES", "p": [5] },
	{ "s": "COMMENTS", "p": [37] },
	{ "s": "COMPARE", "p": [36, 31, 3, 2] },
	{ "s": "COMPASS", "p": [32] },
	{ "s": "COMPLETES", "p": [3] },
	{ "s": "COMPREHENSIVE", "p": [4] },
	{ "s": "COMPRISING", "p": [36] },
	{ "s": "CONCEPT", "p": [20] },
	{ "s": "CONFUSION", "p": [36] },
	{ "s": "CONTACT", "p": [37] },
	{ "s": "CONTAINS", "p": [24] },
	{ "s": "CONTOURS", "p": [33] },
	{ "s": "CONTRACT", "p": [28, 5] },
	{ "s": "CONTROL", "p": [32, 3, 36, 9] },
	{ "s": "CONVERSION", "p": [19, 5] },
	{ "s": "COORDINATE", "p": [13, 19, 5] },
	{ "s": "COORDINATES", "p": [13, 19, 17] },
	{ "s": "COPYRIGHT", "p": [36, 34, 2] },
	{ "s": "CORNER", "p": [23, 17, 15, 14] },
	{ "s": "CORRECT", "p": [14] },
	{ "s": "CORRECTLY", "p": [23] },
	{ "s": "COULD", "p": [36, 31] },
	{ "s": "COUNTY", "p": [5, 2, 18, 36, 28, 14, 15, 34, 26, 25, 24, 21, 20, 19] },
	{ "s": "COVERAGE", "p": [28] },
	{ "s": "COVERS", "p": [28] },
	{ "s": "CREATED", "p": [2] },
	{ "s": "CROSS", "p": [36, 34, 14] },
	{ "s": "CSV", "p": [23, 28, 30] },
	{ "s": "CURRENT", "p": [18, 11, 5] },
	{ "s": "CURSER", "p": [13] },
	{ "s": "CURSOR", "p": [13, 3] },
	{ "s": "CUSTOM", "p": [34, 36, 2] },
	{ "s": "CYAN", "p": [30, 20] },
	{ "s": "CYCLE", "p": [28] }
]